{
  "main": {
    "id": "0e21c48323d871fd",
    "type": "split",
    "children": [
      {
        "id": "6f22ffd0a21daed1",
        "type": "tabs",
        "children": [
          {
            "id": "835b0a5285c155f7",
            "type": "leaf",
            "state": {
              "type": "markdown",
              "state": {
                "file": "Linux Kernel Glossary.md",
                "mode": "source",
                "source": false
              },
              "icon": "lucide-file",
              "title": "Linux Kernel Glossary"
            }
          },
          {
            "id": "69121603877c414b",
            "type": "leaf",
            "state": {
              "type": "markdown",
              "state": {
                "file": "NVMe.md",
                "mode": "source",
                "source": false
              },
              "icon": "lucide-file",
              "title": "NVMe"
            }
          },
          {
            "id": "1881f4509d39da31",
            "type": "leaf",
            "state": {
              "type": "markdown",
              "state": {
                "file": "lsmod의 size.md",
                "mode": "source",
                "source": false
              },
              "icon": "lucide-file",
              "title": "lsmod의 size"
            }
          },
          {
            "id": "2f0adf206eba5679",
            "type": "leaf",
            "state": {
              "type": "markdown",
              "state": {
                "file": "Linux Kernel Source Code.md",
                "mode": "source",
                "source": false
              },
              "icon": "lucide-file",
              "title": "Linux Kernel Source Code"
            }
          },
          {
            "id": "3c1faa80978c58a2",
            "type": "leaf",
            "state": {
              "type": "markdown",
              "state": {
                "file": "Linux Kernel Source Code.md",
                "mode": "source",
                "source": false
              },
              "icon": "lucide-file",
              "title": "Linux Kernel Source Code"
            }
          },
          {
            "id": "3b54590427aa1b6c",
            "type": "leaf",
            "state": {
              "type": "markdown",
              "state": {
                "file": "rodata.md",
                "mode": "source",
                "source": false
              },
              "icon": "lucide-file",
              "title": "rodata"
            }
          }
        ],
        "currentTab": 4
      }
    ],
    "direction": "vertical"
  },
  "left": {
    "id": "30f404e6dad78680",
    "type": "split",
    "children": [
      {
        "id": "8aabccb3b8550233",
        "type": "tabs",
        "children": [
          {
            "id": "481adf52b91e2f40",
            "type": "leaf",
            "state": {
              "type": "file-explorer",
              "state": {
                "sortOrder": "alphabetical",
                "autoReveal": false
              },
              "icon": "lucide-folder-closed",
              "title": "파일 탐색기"
            }
          },
          {
            "id": "f8b057b756c35da4",
            "type": "leaf",
            "state": {
              "type": "search",
              "state": {
                "query": "",
                "matchingCase": false,
                "explainSearch": false,
                "collapseAll": false,
                "extraContext": false,
                "sortOrder": "alphabetical"
              },
              "icon": "lucide-search",
              "title": "검색"
            }
          },
          {
            "id": "701b1610acb29201",
            "type": "leaf",
            "state": {
              "type": "bookmarks",
              "state": {},
              "icon": "lucide-bookmark",
              "title": "북마크"
            }
          }
        ]
      }
    ],
    "direction": "horizontal",
    "width": 300
  },
  "right": {
    "id": "2680b7fc785eedda",
    "type": "split",
    "children": [
      {
        "id": "f0e82ed969bff7dd",
        "type": "tabs",
        "children": [
          {
            "id": "83ca7cfafc90bab7",
            "type": "leaf",
            "state": {
              "type": "backlink",
              "state": {
                "file": "Linux Kernel Glossary.md",
                "collapseAll": false,
                "extraContext": false,
                "sortOrder": "alphabetical",
                "showSearch": false,
                "searchQuery": "",
                "backlinkCollapsed": false,
                "unlinkedCollapsed": true
              },
              "icon": "links-coming-in",
              "title": "Linux Kernel Glossary 의 백링크"
            }
          },
          {
            "id": "f8f8d95cf97237e4",
            "type": "leaf",
            "state": {
              "type": "outgoing-link",
              "state": {
                "file": "Linux Kernel Glossary.md",
                "linksCollapsed": false,
                "unlinkedCollapsed": true
              },
              "icon": "links-going-out",
              "title": "Linux Kernel Glossary 의 나가는 링크"
            }
          },
          {
            "id": "2c31eddd7373c7dc",
            "type": "leaf",
            "state": {
              "type": "tag",
              "state": {
                "sortOrder": "frequency",
                "useHierarchy": true,
                "showSearch": false,
                "searchQuery": ""
              },
              "icon": "lucide-tags",
              "title": "태그"
            }
          },
          {
            "id": "15c61b1ff311cf5f",
            "type": "leaf",
            "state": {
              "type": "all-properties",
              "state": {
                "sortOrder": "frequency",
                "showSearch": false,
                "searchQuery": ""
              },
              "icon": "lucide-archive",
              "title": "모든 속성"
            }
          },
          {
            "id": "92e03d581f597153",
            "type": "leaf",
            "state": {
              "type": "outline",
              "state": {
                "file": "Linux Kernel Glossary.md",
                "followCursor": false,
                "showSearch": false,
                "searchQuery": ""
              },
              "icon": "lucide-list",
              "title": "Linux Kernel Glossary 의 개요"
            }
          }
        ]
      }
    ],
    "direction": "horizontal",
    "width": 300,
    "collapsed": true
  },
  "left-ribbon": {
    "hiddenItems": {
      "switcher:빠른 전환기 열기": false,
      "graph:그래프 뷰 열기": false,
      "canvas:새 캔버스 만들기": false,
      "daily-notes:오늘의 일일 노트 열기": false,
      "templates:템플릿 삽입": false,
      "command-palette:명령어 팔레트 열기": false,
      "bases:새 베이스 생성하기": false
    }
  },
  "active": "3c1faa80978c58a2",
  "lastOpenFiles": [
    "printk_get_level()의 switch 문과 KERN_SOH_ASCII 동작 정리.md",
    "printk_get_level.md",
    "Linux Kernel Source Code.md",
    "lsmod의 size.md",
    "footprint.md",
    "bss.md",
    "rodata.md",
    "NVMe.md",
    "Linux Kernel Glossary.md",
    "BDS.md",
    "PCIe.md",
    "Real Mode.md",
    "TSL.md",
    "BIOS.md",
    "DXE.md",
    "Multi-vector MSI-X.md",
    "Protected Mode.md",
    "16비트 리얼 모드.md",
    "ZB.md",
    "extern.md",
    "glob.md",
    "FAT32.md",
    "Root of Trust.md",
    "MSI.md",
    "ESP.md",
    "UEFI.md"
  ]
}